{"nodes": [{"id": "mc_training_curve_MonteCarloCurve", "label": "Monte Carlo Training Curve (v1 Assignment)", "file_type": "image", "source_file": "game/v1_assignment/artifacts/plots/mc_training_curve.png", "source_location": null, "source_url": null, "captured_at": null, "author": null, "contributor": null}, {"id": "mc_training_curve_MonteCarloAlgorithm", "label": "Monte Carlo Algorithm", "file_type": "image", "source_file": "game/v1_assignment/artifacts/plots/mc_training_curve.png", "source_location": null, "source_url": null, "captured_at": null, "author": null, "contributor": null}, {"id": "concept_RewardImprovement", "label": "Reward Improvement via Training", "file_type": "image", "source_file": "game/v1_assignment/artifacts/plots/mc_training_curve.png", "source_location": null, "source_url": null, "captured_at": null, "author": null, "contributor": null}], "edges": [{"source": "mc_training_curve_MonteCarloCurve", "target": "mc_training_curve_MonteCarloAlgorithm", "relation": "references", "confidence": "EXTRACTED", "confidence_score": 1.0, "source_file": "game/v1_assignment/artifacts/plots/mc_training_curve.png", "source_location": null, "weight": 1.0}, {"source": "mc_training_curve_MonteCarloCurve", "target": "concept_RewardImprovement", "relation": "references", "confidence": "EXTRACTED", "confidence_score": 1.0, "source_file": "game/v1_assignment/artifacts/plots/mc_training_curve.png", "source_location": null, "weight": 1.0}, {"source": "mc_training_curve_MonteCarloCurve", "target": "model_comparison_MonteCarlo", "relation": "references", "confidence": "INFERRED", "confidence_score": 0.9, "source_file": "game/v1_assignment/artifacts/plots/mc_training_curve.png", "source_location": null, "weight": 0.9}], "hyperedges": []}